agentx_dev/ChatModel.py
agentx_dev/Tools.py
agentx_dev/__init__.py
agentx_dev/promptTemplate.yaml
agentx_dev/Agents/Agent.py
agentx_dev/Agents/__init__.py
agentx_dev/Agents/promptTemplate.yaml
agentx_dev/Runner/AgentRun.py
agentx_dev/Runner/__init__.py
agentx_dev/Runner/promptTemplate.yaml
agentx_dev-2.1.dist-info/METADATA
agentx_dev-2.1.dist-info/WHEEL
agentx_dev-2.1.dist-info/top_level.txt
agentx_dev-2.1.dist-info/RECORD
