Metadata-Version: 2.4
Name: agentx-dev
Version: 2.1
Summary: A lightweight LLM agent framework with standard and structured tool support use, prompt management, and support for OpenAI.
Author-email: Bruce-Arhin Shadrach <brucearhin098@gmail.com>
Project-URL: Homepage, https://github.com/shadrach098/Bruce_framework
Project-URL: Bug Tracker, https://github.com/shadrach098/Bruce_framework/issues
Project-URL: Source, https://github.com/shadrach098/Bruce_framework
Requires-Python: >=3.8
Requires-Dist: openai>=1.0.0
Requires-Dist: pydantic>=2.0
Requires-Dist: google-generativeai
Requires-Dist: httpx
Requires-Dist: PyYAML>=5.3.1
